streamlit_cld_video_player/__init__.py
streamlit_cld_video_player/frontend/index.html
streamlit_cld_video_player/frontend/main.js
streamlit_cld_video_player/frontend/streamlit-component-lib.js
streamlit_cld_video_player/frontend/style.css
streamlit_cld_video_player-0.1.0.dist-info/LICENSE
streamlit_cld_video_player-0.1.0.dist-info/METADATA
streamlit_cld_video_player-0.1.0.dist-info/WHEEL
streamlit_cld_video_player-0.1.0.dist-info/top_level.txt
streamlit_cld_video_player-0.1.0.dist-info/RECORD
