Metadata-Version: 2.1
Name: streamlit_cld_video_player
Version: 0.1.0
Summary: Load and play videos hosted on Cloudinary using the player
Author: Akshay Ranganath
Author-email: support@cloudinary.com
Requires-Python: >=3.7
License-File: LICENSE
Requires-Dist: streamlit >=1.2
Requires-Dist: jinja2
